opcng/__init__.py
py_opc_ng-0.0.5.dist-info/LICENSE
py_opc_ng-0.0.5.dist-info/METADATA
py_opc_ng-0.0.5.dist-info/WHEEL
py_opc_ng-0.0.5.dist-info/top_level.txt
py_opc_ng-0.0.5.dist-info/RECORD
