Metadata-Version: 2.1
Name: py-opc-ng
Version: 0.0.5
Summary: Python library to operate Alphasense OPC particle counters
Home-page: https://github.com/fargiolas/py-opc-ng
Author: Filippo Argiolas
Author-email: filippo.argiolas@gmail.com
License: LGPLv3
Keywords: alphasense,opc,particulates sensors,air quality,optical particle counter,opc-n2,opc-n3,opc-r1,opc-r2
Classifier: Operating System :: OS Independent
Classifier: Intended Audience :: Science/Research
Classifier: Intended Audience :: Developers
Classifier: Intended Audience :: Education
Classifier: Programming Language :: Python :: 3
Classifier: Topic :: Scientific/Engineering :: Atmospheric Science
Classifier: Topic :: Software Development
Classifier: Topic :: System :: Hardware
License-File: LICENSE
